setup.py
neutron_pardnet_lbaas/__init__.py
neutron_pardnet_lbaas/pardnet_client.py
neutron_pardnet_lbaas/pardnet_driver.py
neutron_pardnet_lbaas.egg-info/PKG-INFO
neutron_pardnet_lbaas.egg-info/SOURCES.txt
neutron_pardnet_lbaas.egg-info/dependency_links.txt
neutron_pardnet_lbaas.egg-info/not-zip-safe
neutron_pardnet_lbaas.egg-info/top_level.txt