Metadata-Version: 1.1
Name: neutron-pardnet-lbaas
Version: 0.0.1
Summary: pardnet driver for Openstack Neutron LBaaS service
Home-page: https://pypi.python.org/pypi/neutron_pardnet_lbaas
Author: jaff cheng, pardnet
Author-email: 312973099@qq.com
License: UNKNOWN
Keywords: openstack,pardnet,lbaas
Platform: UNKNOWN
Classifier: Environment :: OpenStack
Classifier: Operating System :: POSIX :: Linux
Classifier: Programming Language :: Python :: 2.7
